trisigma_cli/__init__.py
trisigma_cli/cli/__init__.py
trisigma_cli/cli/commands/__init__.py
trisigma_cli/cli/commands/compile.py
trisigma_cli/cli/commands/init.py
trisigma_cli/cli/commands/listing.py
trisigma_cli/cli/commands/login.py
trisigma_cli/cli/commands/self_update.py
trisigma_cli/cli/commands/validate.py
trisigma_cli/cli/commands/workflow.py
trisigma_cli/cli/interactive/__init__.py
trisigma_cli/cli/interactive/app.py
trisigma_cli/cli/interactive/widgets/__init__.py
trisigma_cli/cli/interactive/widgets/ai_explain_dialog.py
trisigma_cli/cli/interactive/widgets/base_dialog.py
trisigma_cli/cli/interactive/widgets/branch_dialog.py
trisigma_cli/cli/interactive/widgets/compile_dialog.py
trisigma_cli/cli/interactive/widgets/dropdown_widgets.py
trisigma_cli/cli/interactive/widgets/filtered_widgets.py
trisigma_cli/cli/interactive/widgets/main_menu.py
trisigma_cli/cli/interactive/widgets/metrics_compile_dialog.py
trisigma_cli/cli/interactive/widgets/no_scroll.py
trisigma_cli/cli/interactive/widgets/progress_panel.py
trisigma_cli/cli/interactive/widgets/publish_dialog.py
trisigma_cli/cli/interactive/widgets/save_dialog.py
trisigma_cli/cli/interactive/widgets/settings_dialog.py
trisigma_cli/cli/interactive/widgets/sql_view_dialog.py
trisigma_cli/cli/interactive/widgets/status_panel.py
trisigma_cli/cli/interactive/widgets/update_banner.py
trisigma_cli/cli/main.py
trisigma_cli/core/__init__.py
trisigma_cli/core/api_client.py
trisigma_cli/core/auth_server.py
trisigma_cli/core/backend_llm_client.py
trisigma_cli/core/cli_config_client.py
trisigma_cli/core/config.py
trisigma_cli/core/constants.py
trisigma_cli/core/dto.py
trisigma_cli/core/file_monitor.py
trisigma_cli/core/git_wrapper.py
trisigma_cli/core/jwt_decoder.py
trisigma_cli/core/llm_explain_service.py
trisigma_cli/core/mde_constants.py
trisigma_cli/core/oauth_service.py
trisigma_cli/core/rag_analyzer.py
trisigma_cli/core/repository.py
trisigma_cli/core/services/__init__.py
trisigma_cli-0.1.3.dist-info/LICENSE
trisigma_cli-0.1.3.dist-info/METADATA
trisigma_cli-0.1.3.dist-info/WHEEL
trisigma_cli-0.1.3.dist-info/entry_points.txt
trisigma_cli-0.1.3.dist-info/RECORD
