Metadata-Version: 2.3
Name: trisigma-cli
Version: 0.1.3
Summary: Trisigma CLI - инструмент командной строки для работы с Репозиторием метрик. Помогает создавать, валидировать и публиковать изменния в семантическом слое.
License: Proprietary
Keywords: cli,metrics,analytics,trisigma,data-quality,semantic-layer
Author: Vlad Bozhev
Author-email: vabozhev@avito.ru
Requires-Python: >=3.9,<4.0
Classifier: Development Status :: 4 - Beta
Classifier: Environment :: Console
Classifier: Intended Audience :: Developers
Classifier: Intended Audience :: System Administrators
Classifier: License :: Other/Proprietary License
Classifier: Operating System :: MacOS
Classifier: Operating System :: POSIX :: Linux
Classifier: Programming Language :: Python :: 3
Classifier: Programming Language :: Python :: 3.9
Classifier: Programming Language :: Python :: 3.10
Classifier: Programming Language :: Python :: 3.11
Classifier: Programming Language :: Python :: 3.12
Classifier: Programming Language :: Python :: 3.13
Classifier: Topic :: Software Development :: Libraries :: Python Modules
Classifier: Topic :: Software Development :: Quality Assurance
Classifier: Topic :: Utilities
Requires-Dist: aiohttp (>=3.12.0,<4.0.0)
Requires-Dist: gitpython (>=3.1.0,<4.0.0)
Requires-Dist: httpx (>=0.25.0,<0.26.0)
Requires-Dist: openai (>=1.101.0,<2.0.0)
Requires-Dist: packaging (>=25.0,<26.0)
Requires-Dist: pydantic (>=2.0.0,<3.0.0)
Requires-Dist: pyjwt (>=2.10.1,<3.0.0)
Requires-Dist: pyperclip (>=1.9.0,<2.0.0)
Requires-Dist: pyyaml (>=6.0.0,<7.0.0)
Requires-Dist: rich (>=13.0.0,<14.0.0)
Requires-Dist: tenacity (>=9.0.0,<10.0.0)
Requires-Dist: textual (>=5.3.0,<6.0.0)
Requires-Dist: transliterate (>=1.10.2,<2.0.0)
Requires-Dist: typer[all] (>=0.16.1,<0.17.0)
Requires-Dist: watchdog (>=6.0.0,<7.0.0)
Project-URL: Documentation, https://trisigma.io/
Project-URL: Homepage, https://trisigma.io/
